dkutils/__init__.py
dkutils/constants.py
dkutils/decorators.py
dkutils/dictionary_comparator.py
dkutils/util.py
dkutils/validation.py
dkutils/wait_loop.py
dkutils/alteryx_api/__init__.py
dkutils/alteryx_api/gallery_client.py
dkutils/datakitchen_api/__init__.py
dkutils/datakitchen_api/datakitchen_client.py
dkutils/datakitchen_api/datetime_utils.py
dkutils/datakitchen_api/kitchen.py
dkutils/datakitchen_api/order_run_monitor.py
dkutils/datakitchen_api/recipe.py
dkutils/datakitchen_api/tests_utils.py
dkutils/datakitchen_api/vault.py
dkutils/gmail_api/__init__.py
dkutils/gmail_api/gmail_client.py
dkutils/jira_api/__init__.py
dkutils/jira_api/jira_client.py
dkutils/reporting/__init__.py
dkutils/reporting/dataframe_wrapper.py
dkutils/smtp_api/__init__.py
dkutils/smtp_api/sender.py
dkutils/ssh/__init__.py
dkutils/ssh/remote_client.py
dkutils/streamsets_api/__init__.py
dkutils/streamsets_api/datacollector_client.py
dkutils/veeva_network_api/__init__.py
dkutils/veeva_network_api/veeva_network_client.py
DKUtils-2.11.6.dist-info/LICENSE
DKUtils-2.11.6.dist-info/METADATA
DKUtils-2.11.6.dist-info/WHEEL
DKUtils-2.11.6.dist-info/top_level.txt
DKUtils-2.11.6.dist-info/RECORD
