Metadata-Version: 2.1
Name: DKUtils
Version: 2.11.6
Summary: DataKitchen Utils Library
Home-page: https://github.com/DataKitchen/DKUtils
Author: DataKitchen
Author-email: info@datakitchen.io
License: UNKNOWN
Project-URL: Documentation, https://datakitchen.github.io/DKUtils
Project-URL: Source Code, https://github.com/DataKitchen/DKUtils
Project-URL: Download, https://pypi.org/project/DKUtils
Platform: UNKNOWN
Classifier: Programming Language :: Python :: 3
Requires-Python: >=3.8
Requires-Dist: dataclasses (>=0.6)
Requires-Dist: events-ingestion-client (~=1.0)
Requires-Dist: jira (>=2.0.0)
Requires-Dist: pandas (>=1.1.2)
Requires-Dist: paramiko (>=2.10.4)
Requires-Dist: scp (>=0.13.2)
Requires-Dist: Sphinx (>=4.5.0)
Requires-Dist: sphinx-rtd-theme (>=0.4.3)
Requires-Dist: google-api-python-client (>=1.10.1)
Requires-Dist: google-auth-httplib2 (>=0.0.4)
Requires-Dist: google-auth-oauthlib (>=0.4.2)
Requires-Dist: sqlalchemy (>=1.4.27)
